crawldad/__init__.py
crawldad/crawler.py
crawldad/page.py
crawldad-0.0.2.dist-info/METADATA
crawldad-0.0.2.dist-info/WHEEL
crawldad-0.0.2.dist-info/top_level.txt
crawldad-0.0.2.dist-info/RECORD
