Metadata-Version: 2.1
Name: crawldad
Version: 0.0.2
Requires-Dist: beautifulsoup4 >=4.12.2
Requires-Dist: requests >=2.31.0
